query_client/__init__.py
query_client-0.0.1.dist-info/LICENSE
query_client-0.0.1.dist-info/METADATA
query_client-0.0.1.dist-info/WHEEL
query_client-0.0.1.dist-info/top_level.txt
query_client-0.0.1.dist-info/RECORD
