Metadata-Version: 2.1
Name: query-client
Version: 0.0.1
Summary: A simple query client for pcd label dataset
Home-page: http://mirrors.sxc.sh/pypi/simple/query_client
Author: liuyixiong
Author-email: liuyixiong@saicmotor.com
Classifier: Programming Language :: Python :: 3
Classifier: License :: OSI Approved :: MIT License
Classifier: Operating System :: OS Independent
License-File: LICENSE
Requires-Dist: sql-metadata
Requires-Dist: trino[sqlalchemy]
